[
  {
    "text": "Ο Σπύρος θέλει να πληρώσει με κάρτα αλλά το κατάστημα δεν δέχεται κάρτα. Πηγαίνει στο ΑΤΜ να κάνει ανάληψη. Παίρνει 50 ευρώ. Επιστρέφει, πληρώνει και λέει «κρατήστε τα ρέστα».",
    "statements": [
      {"id": 1, "text": "Το κατάστημα δέχεται κάρτα.", "correct": false},
      {"id": 2, "text": "Ο Σπύρος πηγαίνει στο ΑΤΜ.", "correct": true},
      {"id": 3, "text": "Ο Σπύρος θέλει τα ρέστα.", "correct": false},
      {"id": 4, "text": "Ο Σπύρος κάνει ανάληψη 50 ευρώ.", "correct": true}
    ]
  },
  {
    "text": "Η Ιωάννα αγοράζει φρούτα στη λαϊκή αγορά. Ρωτάει: «Πόσα χρωστάω;» Ο πωλητής λέει «Τρία ευρώ και πενήντα». Η Ιωάννα δίνει πέντε ευρώ και παίρνει ρέστα.",
    "statements": [
      {"id": 1, "text": "Η Ιωάννα αγοράζει λαχανικά.", "correct": false},
      {"id": 2, "text": "Τα φρούτα κοστίζουν 3,50 ευρώ.", "correct": true},
      {"id": 3, "text": "Η Ιωάννα πληρώνει με κάρτα.", "correct": false},
      {"id": 4, "text": "Η Ιωάννα παίρνει ρέστα.", "correct": true}
    ]
  }
]
